{
    "Pruning Time": 170.81745100021362,
    "Cut Data": [
        {
            "Rule": [
                "Canopy",
                "Canopy",
                "Vigor",
                "Vigor",
                "Spacing",
                "Canopy",
                "Spacing",
                "Canopy",
                "Spacing",
                "Canopy",
                "Canopy",
                "Canopy",
                "Vigor",
                "Vigor",
                "Vigor"
            ],
            "Sequence": [
                1,
                2,
                3,
                4,
                5,
                6,
                7,
                8,
                9,
                10,
                11,
                12,
                13,
                14,
                15
            ],
            "Vertices": [
                [
                    [
                        -0.5436356741335318,
                        1.411043117758562,
                        0.16164746125544838
                    ],
                    [
                        -0.5116215471019888,
                        1.422373076518784,
                        0.2000609106432865
                    ],
                    [
                        -0.516841088003152,
                        1.3736470218760466,
                        0.2042876115256566
                    ],
                    [
                        -0.5490118171715667,
                        1.3608551329532153,
                        0.1660009760478215
                    ],
                    [
                        -0.5477797843920169,
                        1.411043117758562,
                        0.16500329557456925
                    ],
                    [
                        -0.5156449432133019,
                        1.422373076518784,
                        0.20331899257344674
                    ],
                    [
                        -0.5531559274300518,
                        1.3608551329532153,
                        0.16935681036694236
                    ],
                    [
                        -0.5208644841144651,
                        1.3736470218760466,
                        0.20754569345581686
                    ]
                ],
                [
                    [
                        -0.6170276182679562,
                        1.5074703023959024,
                        -0.022376434055360467
                    ],
                    [
                        -0.5862663083313859,
                        1.5151454357496017,
                        0.017051526612503268
                    ],
                    [
                        -0.5610804338869902,
                        1.4857556791205921,
                        -0.0033435923746225607
                    ],
                    [
                        -0.5911631345637828,
                        1.477288666928813,
                        -0.04332107998583255
                    ],
                    [
                        -0.6170276182679562,
                        1.5035234731425138,
                        -0.022376434055360467
                    ],
                    [
                        -0.5862663083313859,
                        1.511302159882731,
                        0.017051526612503268
                    ],
                    [
                        -0.5911631345637828,
                        1.4733418376754241,
                        -0.04332107998583255
                    ],
                    [
                        -0.5610804338869902,
                        1.4819124032537216,
                        -0.0033435923746225607
                    ]
                ],
                [
                    [
                        -0.4092363342000351,
                        1.4314163494357564,
                        -0.0018589174243847275
                    ],
                    [
                        -0.3818158698500648,
                        1.4418935156011226,
                        0.0402744066568728
                    ],
                    [
                        -0.39608951084531274,
                        1.4335654578244046,
                        0.05183297323038231
                    ],
                    [
                        -0.4239275808936077,
                        1.4228446366319367,
                        0.01003781957579938
                    ],
                    [
                        -0.4092363342000351,
                        1.4277733714941327,
                        -0.0018589174243847275
                    ],
                    [
                        -0.3818158698500648,
                        1.4383540910460173,
                        0.0402744066568728
                    ],
                    [
                        -0.4239275808936077,
                        1.4192016586903133,
                        0.01003781957579938
                    ],
                    [
                        -0.39608951084531274,
                        1.4300260332692993,
                        0.05183297323038231
                    ]
                ],
                [
                    [
                        -0.41136330426382156,
                        1.4020516636903457,
                        0.0034767953638595696
                    ],
                    [
                        -0.3709418430876022,
                        1.4186902003468218,
                        0.06522725772047797
                    ],
                    [
                        -0.3621577673612367,
                        1.4063898842289775,
                        0.05811405345089146
                    ],
                    [
                        -0.4021959334684615,
                        1.3892146205835827,
                        -0.003946795132601163
                    ],
                    [
                        -0.41136330426382156,
                        1.3984145014767628,
                        0.0034767953638595696
                    ],
                    [
                        -0.3709418430876022,
                        1.4152051107800991,
                        0.06522725772047797
                    ],
                    [
                        -0.4021959334684615,
                        1.38557745837,
                        -0.003946795132601163
                    ],
                    [
                        -0.3621577673612367,
                        1.4029047946622548,
                        0.05811405345089146
                    ]
                ],
                [
                    [
                        -0.36058671267069686,
                        1.5129243316592993,
                        -0.03919039000735406
                    ],
                    [
                        -0.36773125604666884,
                        1.5223659639594842,
                        0.010503797640216453
                    ],
                    [
                        -0.33419977116275507,
                        1.524157151288778,
                        0.012261108299045255
                    ],
                    [
                        -0.3259149066818198,
                        1.5147764327453683,
                        -0.03737331765174455
                    ],
                    [
                        -0.36058671267069686,
                        1.509775759812982,
                        -0.03919039000735406
                    ],
                    [
                        -0.36773125604666884,
                        1.5193209454996852,
                        0.010503797640216453
                    ],
                    [
                        -0.3259149066818198,
                        1.511627860899051,
                        -0.03737331765174455
                    ],
                    [
                        -0.33419977116275507,
                        1.5211121328289787,
                        0.012261108299045255
                    ]
                ],
                [
                    [
                        -0.23689106186000258,
                        1.5364864617747527,
                        -0.0026811926027200486
                    ],
                    [
                        -0.27925775239247963,
                        1.54629357661559,
                        0.02645330437864129
                    ],
                    [
                        -0.2547224680343792,
                        1.5415661277326507,
                        0.04854497364267245
                    ],
                    [
                        -0.21140735708690972,
                        1.5315762716214871,
                        0.020264438238664948
                    ],
                    [
                        -0.23689106186000258,
                        1.5337040206879022,
                        -0.0026811926027200486
                    ],
                    [
                        -0.27925775239247963,
                        1.543614688915258,
                        0.02645330437864129
                    ],
                    [
                        -0.21140735708690972,
                        1.528793830534637,
                        0.020264438238664948
                    ],
                    [
                        -0.2547224680343792,
                        1.5388872400323184,
                        0.04854497364267245
                    ]
                ],
                [
                    [
                        -0.4284270424320057,
                        1.9848706172161594,
                        0.07393702140605794
                    ],
                    [
                        -0.4717996139602409,
                        1.9764021291608123,
                        0.10628706518611444
                    ],
                    [
                        -0.4828344131663568,
                        1.9508170875268014,
                        0.09635128735291307
                    ],
                    [
                        -0.439991586180972,
                        1.9580573215893882,
                        0.06352425944402929
                    ],
                    [
                        -0.4284270424320057,
                        1.982471532870606,
                        0.07393702140605794
                    ],
                    [
                        -0.4717996139602409,
                        1.9741129412251375,
                        0.10628706518611444
                    ],
                    [
                        -0.439991586180972,
                        1.955658237243835,
                        0.06352425944402929
                    ],
                    [
                        -0.4828344131663568,
                        1.9485278995911266,
                        0.09635128735291307
                    ]
                ],
                [
                    [
                        -0.6679987424408352,
                        2.0453577087991377,
                        0.086874205178641
                    ],
                    [
                        -0.6761709403422276,
                        2.0354896802015254,
                        0.13644828037107787
                    ],
                    [
                        -0.6792675687164423,
                        2.013685080182866,
                        0.13561854129894765
                    ],
                    [
                        -0.6712251328382808,
                        2.022639402428847,
                        0.08600969647717786
                    ],
                    [
                        -0.6679987424408352,
                        2.0427829674105045,
                        0.086874205178641
                    ],
                    [
                        -0.6761709403422276,
                        2.0330184921994103,
                        0.13644828037107787
                    ],
                    [
                        -0.6712251328382808,
                        2.020064661040214,
                        0.08600969647717786
                    ],
                    [
                        -0.6792675687164423,
                        2.0112138921807508,
                        0.13561854129894765
                    ]
                ],
                [
                    [
                        -0.20528540120576144,
                        1.9989031398037596,
                        0.050101518087790384
                    ],
                    [
                        -0.1850263151811034,
                        1.9997277746679172,
                        0.09658322182806248
                    ],
                    [
                        -0.17493615287914097,
                        1.9630363031377382,
                        0.0964964057775753
                    ],
                    [
                        -0.19478804383843215,
                        1.9607309600648306,
                        0.050011198519094566
                    ],
                    [
                        -0.2087532781931827,
                        1.9992163497159525,
                        0.0520790476453107
                    ],
                    [
                        -0.18835967237014453,
                        2.000028835090843,
                        0.09848404252931907
                    ],
                    [
                        -0.19825592082585342,
                        1.9610441699770234,
                        0.05198872807661487
                    ],
                    [
                        -0.17826951006818212,
                        1.9633373635606641,
                        0.09839722647883188
                    ]
                ],
                [
                    [
                        -0.22586069402099496,
                        2.175483429196995,
                        -0.0030371191989530233
                    ],
                    [
                        -0.2053107543782183,
                        2.1696036122794418,
                        0.044336447770778616
                    ],
                    [
                        -0.16834902092720358,
                        2.170852698530017,
                        0.022532741062972386
                    ],
                    [
                        -0.1874446924793844,
                        2.176781661039701,
                        -0.025698697872204183
                    ],
                    [
                        -0.22586069402099496,
                        2.1727816371530264,
                        -0.002609197378195745
                    ],
                    [
                        -0.2053107543782183,
                        2.167004098707966,
                        0.04474817027291282
                    ],
                    [
                        -0.1874446924793844,
                        2.174079868995732,
                        -0.025270776051446904
                    ],
                    [
                        -0.16834902092720358,
                        2.1682531849585414,
                        0.022944463565106592
                    ]
                ],
                [
                    [
                        -0.40837475286179575,
                        2.147644809202408,
                        -0.073954651398091
                    ],
                    [
                        -0.3838110332889736,
                        2.14332771962945,
                        -0.02917483919283236
                    ],
                    [
                        -0.35725743521137254,
                        2.1529447008566347,
                        -0.04621984582061988
                    ],
                    [
                        -0.38089042320621336,
                        2.1575988757498883,
                        -0.09159710345941342
                    ],
                    [
                        -0.40837475286179575,
                        2.144624545013277,
                        -0.07347628854486324
                    ],
                    [
                        -0.3838110332889736,
                        2.1404097339128123,
                        -0.028712675658227663
                    ],
                    [
                        -0.38089042320621336,
                        2.1545786115607575,
                        -0.09111874060618566
                    ],
                    [
                        -0.35725743521137254,
                        2.1500267151399965,
                        -0.045757682286015185
                    ]
                ],
                [
                    [
                        -0.5176765324303993,
                        2.124124834879129,
                        -0.011602043125123062
                    ],
                    [
                        -0.5344130238650273,
                        2.1175027765873824,
                        0.037315409695760304
                    ],
                    [
                        -0.5135240321081028,
                        2.124431572224979,
                        0.04188495440690698
                    ],
                    [
                        -0.4957494444876283,
                        2.1313979629003845,
                        -0.006805411008758521
                    ],
                    [
                        -0.5176765324303993,
                        2.1219644675725293,
                        -0.011259874558371834
                    ],
                    [
                        -0.5344130238650273,
                        2.1154446877532758,
                        0.03764137894388846
                    ],
                    [
                        -0.4957494444876283,
                        2.129237595593785,
                        -0.006463242442007292
                    ],
                    [
                        -0.5135240321081028,
                        2.1223734833908723,
                        0.04221092365503514
                    ]
                ],
                [
                    [
                        -0.8164522837913916,
                        2.1476964677162473,
                        0.0960787494311122
                    ],
                    [
                        -0.8006366667972672,
                        2.1415181934226037,
                        0.14740875580147442
                    ],
                    [
                        -0.7631575935969259,
                        2.1215195371791222,
                        0.149913877440675
                    ],
                    [
                        -0.7771599031296973,
                        2.1267302391854392,
                        0.09870507352736603
                    ],
                    [
                        -0.8164522837913916,
                        2.145480205576291,
                        0.09642977086976151
                    ],
                    [
                        -0.8006366667972672,
                        2.1394042097551407,
                        0.14774357792150064
                    ],
                    [
                        -0.7771599031296973,
                        2.1245139770454826,
                        0.09905609496601557
                    ],
                    [
                        -0.7631575935969259,
                        2.119405553511659,
                        0.15024869956070147
                    ]
                ],
                [
                    [
                        -0.7181949856526124,
                        2.1164322264759563,
                        0.09613752908980745
                    ],
                    [
                        -0.7069462170796731,
                        2.111710353675079,
                        0.1473175724135211
                    ],
                    [
                        -0.6777079003172363,
                        2.1103832456544294,
                        0.14701104729646153
                    ],
                    [
                        -0.6875463186424565,
                        2.1150411035826013,
                        0.09581621831397383
                    ],
                    [
                        -0.7181949856526124,
                        2.114209587914493,
                        0.0964895604544084
                    ],
                    [
                        -0.7069462170796731,
                        2.1095899935861087,
                        0.14765340445949898
                    ],
                    [
                        -0.6875463186424565,
                        2.112818465021138,
                        0.09616824967857503
                    ],
                    [
                        -0.6777079003172363,
                        2.1082628855654595,
                        0.14734687934243965
                    ]
                ],
                [
                    [
                        -0.6048941654707655,
                        1.3713733802280699,
                        -0.025722103552776595
                    ],
                    [
                        -0.5662354412950567,
                        1.3898687782267465,
                        0.007896297635691468
                    ],
                    [
                        -0.5430802318791272,
                        1.3527254923694616,
                        -0.009664625835934668
                    ],
                    [
                        -0.5810359629095239,
                        1.3331024226281973,
                        -0.04381617740987982
                    ],
                    [
                        -0.6048941654707655,
                        1.3677036420307482,
                        -0.025140874122256178
                    ],
                    [
                        -0.5662354412950567,
                        1.3863071705891845,
                        0.008460400868022362
                    ],
                    [
                        -0.5810359629095239,
                        1.3294326844308755,
                        -0.04323494797935941
                    ],
                    [
                        -0.5430802318791272,
                        1.3491638847318994,
                        -0.009100522603603773
                    ]
                ]
            ],
            "Cut Time": [
                0.6857438087463379,
                0.6053450107574463,
                0.6300723552703857,
                0.9829373359680176,
                0.6654493808746338,
                0.6914536952972412,
                0.7176315784454346,
                0.6300380229949951,
                1.6438052654266357,
                0.8544549942016602,
                0.6743838787078857,
                1.1788322925567627,
                1.4033513069152832,
                0.8184309005737305,
                0.6464848518371582
            ],
            "Rule Time": [
                3.021145820617676,
                1.6481740474700928,
                0.8110518455505371,
                1.2770235538482666,
                0.9488785266876221,
                1.655961513519287,
                3.671224355697632,
                1.3903796672821045,
                1.4081368446350098,
                1.2352204322814941,
                0.983123779296875,
                1.5829758644104004,
                1.0210025310516357,
                1.1340837478637695,
                0.910327672958374
            ],
            "Between Time": [
                2.276123046875,
                4.172887563705444,
                3.313969612121582,
                8.123000621795654,
                8.958310842514038,
                7.123204708099365,
                5.015357971191406,
                8.951342821121216,
                18.676477670669556,
                8.52902603149414,
                2.1065080165863037,
                6.282583951950073,
                6.390748500823975,
                0.8019390106201172,
                12.680848121643066
            ]
        }
    ],
    "Explanations": [],
    "Reset Answer": ""
}