{
    "Pruning Time": 353.68575406074524,
    "Cut Data": [
        {
            "Rule": [
                "Canopy",
                "Spacing",
                "Spacing",
                "Canopy",
                "Spacing",
                "Spacing",
                "Vigor",
                "Vigor",
                "Spacing",
                "Canopy",
                "Vigor",
                "Canopy",
                "Canopy",
                "Vigor"
            ],
            "Sequence": [
                1,
                2,
                3,
                4,
                5,
                6,
                7,
                8,
                9,
                10,
                11,
                12,
                13,
                14
            ],
            "Vertices": [
                [
                    [
                        0.13849579474979756,
                        1.7975305692419115,
                        0.16073110634972348
                    ],
                    [
                        0.1374492975551052,
                        1.8030346429381796,
                        0.21073110634972372
                    ],
                    [
                        0.2358874511285248,
                        1.8231892376142727,
                        0.21073110634972372
                    ],
                    [
                        0.23968474094926556,
                        1.818248371459018,
                        0.16073110634972348
                    ],
                    [
                        0.13849579474979756,
                        1.7937213187888117,
                        0.16073110634972348
                    ],
                    [
                        0.1374492975551052,
                        1.7993289458715978,
                        0.21073110634972372
                    ],
                    [
                        0.23968474094926556,
                        1.8144391210059183,
                        0.16073110634972348
                    ],
                    [
                        0.2358874511285248,
                        1.8194835405476912,
                        0.21073110634972372
                    ]
                ],
                [
                    [
                        0.8416483937438418,
                        1.6117441530595469,
                        0.04047008474112631
                    ],
                    [
                        0.8492216710663021,
                        1.6209414769023265,
                        0.09438792121850814
                    ],
                    [
                        0.8183794171678411,
                        1.575134995714003,
                        0.10981852592154497
                    ],
                    [
                        0.8098221644193087,
                        1.5644762854241587,
                        0.056392979530588305
                    ],
                    [
                        0.8372974131822378,
                        1.6116126830545734,
                        0.04297868187636801
                    ],
                    [
                        0.8450052103030783,
                        1.6208140715715824,
                        0.09681895974918434
                    ],
                    [
                        0.8054711838577048,
                        1.564344815419185,
                        0.05890157666583037
                    ],
                    [
                        0.8141629564046173,
                        1.575007590383259,
                        0.1122495644522215
                    ]
                ],
                [
                    [
                        0.012046209568226269,
                        1.5341430924705857,
                        0.18990008833595254
                    ],
                    [
                        0.04171456715219583,
                        1.5444991185110621,
                        0.2339245030771108
                    ],
                    [
                        -0.009933427927572026,
                        1.4522858703229335,
                        0.2589517173446693
                    ],
                    [
                        -0.04106826921676639,
                        1.4393115582160787,
                        0.2156379207379393
                    ],
                    [
                        0.007592624539449528,
                        1.5320827061977347,
                        0.1923669152659303
                    ],
                    [
                        0.0373839450145918,
                        1.5424956192295687,
                        0.2363232212431663
                    ],
                    [
                        -0.04552185424554313,
                        1.4372511719432277,
                        0.21810474766791685
                    ],
                    [
                        -0.014264050065176058,
                        1.4502823710414403,
                        0.26135043551072457
                    ]
                ],
                [
                    [
                        -0.49780651667607967,
                        1.72544717218704,
                        0.0596231499841592
                    ],
                    [
                        -0.4629926565055168,
                        1.7294853318775312,
                        0.09752166490854096
                    ],
                    [
                        -0.34543067201553423,
                        1.7216582869023835,
                        0.029143876250537087
                    ],
                    [
                        -0.3776033349897982,
                        1.7174442815136988,
                        -0.010290842953451963
                    ],
                    [
                        -0.49780651667607967,
                        1.7207408262320987,
                        0.05937650084412284
                    ],
                    [
                        -0.4629926565055168,
                        1.724882397392791,
                        0.09728043533401022
                    ],
                    [
                        -0.3776033349897982,
                        1.7127379355587575,
                        -0.010537492093488327
                    ],
                    [
                        -0.34543067201553423,
                        1.7170553524176433,
                        0.028902646676006352
                    ]
                ],
                [
                    [
                        0.18505269940439983,
                        2.337054754816012,
                        0.14116900635763352
                    ],
                    [
                        0.20241246069170693,
                        2.340618225590766,
                        0.1889883933565869
                    ],
                    [
                        0.1750070955127461,
                        2.303802368335225,
                        0.2064554596967753
                    ],
                    [
                        0.15649209003401915,
                        2.2986869640259653,
                        0.15937237841018437
                    ],
                    [
                        0.1818805062696166,
                        2.3359930533690214,
                        0.14233345927190758
                    ],
                    [
                        0.19936857916419706,
                        2.339599468760739,
                        0.19010574547381734
                    ],
                    [
                        0.15331989689923584,
                        2.297625262578974,
                        0.16053683132445845
                    ],
                    [
                        0.17196321398523617,
                        2.3027836115051974,
                        0.20757281181400575
                    ]
                ],
                [
                    [
                        0.2327553164446089,
                        2.2002910652480736,
                        0.17640084862762762
                    ],
                    [
                        0.24916135145779872,
                        2.2099616545687297,
                        0.22572906810099314
                    ],
                    [
                        0.30604716900337753,
                        2.2315291107835855,
                        0.2041698792604314
                    ],
                    [
                        0.2921975545376297,
                        2.2228277522941386,
                        0.15387280048757465
                    ],
                    [
                        0.23446110794520064,
                        2.2023437753142407,
                        0.17537763764461248
                    ],
                    [
                        0.25079378232154936,
                        2.211926084140093,
                        0.22474986214984197
                    ],
                    [
                        0.2939033460382215,
                        2.2248804623603053,
                        0.1528495895045595
                    ],
                    [
                        0.3076795998671282,
                        2.2334935403549485,
                        0.2031906733092802
                    ]
                ],
                [
                    [
                        -0.5989178789341556,
                        2.263628454470715,
                        0.1311554651331045
                    ],
                    [
                        -0.61343077241944,
                        2.269602519417513,
                        0.1806518145135532
                    ],
                    [
                        -0.5984450492323856,
                        2.289219332616637,
                        0.18435272648691772
                    ],
                    [
                        -0.5832071212226271,
                        2.2841943621280776,
                        0.13503543346025562
                    ],
                    [
                        -0.5989178789341556,
                        2.261461017244293,
                        0.13173622818756972
                    ],
                    [
                        -0.61343077241944,
                        2.267535107081528,
                        0.18120577597940266
                    ],
                    [
                        -0.5832071212226271,
                        2.2820269249016545,
                        0.13561619651472084
                    ],
                    [
                        -0.5984450492323856,
                        2.287151920280652,
                        0.18490668795276718
                    ]
                ],
                [
                    [
                        -0.5783171738345293,
                        2.2842024438791295,
                        0.13204092466777742
                    ],
                    [
                        -0.5937104663852473,
                        2.2892041983615776,
                        0.18127157438008526
                    ],
                    [
                        -0.646411626468638,
                        2.2833833050508523,
                        0.15133089971820846
                    ],
                    [
                        -0.6335559547535797,
                        2.2781012679309045,
                        0.10065857244632768
                    ],
                    [
                        -0.5783171738345293,
                        2.2820251079541984,
                        0.1326243400705139
                    ],
                    [
                        -0.5937104663852473,
                        2.287126887327085,
                        0.18182818819420596
                    ],
                    [
                        -0.6335559547535797,
                        2.2759239320059743,
                        0.10124198784906416
                    ],
                    [
                        -0.646411626468638,
                        2.2813059940163596,
                        0.15188751353232915
                    ]
                ],
                [
                    [
                        -0.794345242642572,
                        2.289160396868017,
                        0.15031386240185254
                    ],
                    [
                        -0.8005202390964036,
                        2.2945505130898756,
                        0.2049503830168124
                    ],
                    [
                        -0.7957868713169753,
                        2.317858894819016,
                        0.20153413525680347
                    ],
                    [
                        -0.7893529339615459,
                        2.3137438735530074,
                        0.14671072735222646
                    ],
                    [
                        -0.7969387470023651,
                        2.288772851468692,
                        0.148867523281331
                    ],
                    [
                        -0.8029792236578165,
                        2.2941830688825084,
                        0.2035790625659712
                    ],
                    [
                        -0.7919464383213389,
                        2.313356328153682,
                        0.14526438823170512
                    ],
                    [
                        -0.7982458558783883,
                        2.317491450611649,
                        0.20016281480596246
                    ]
                ],
                [
                    [
                        -0.8208620214269574,
                        1.7153503473256877,
                        0.04007665340046881
                    ],
                    [
                        -0.8235713168225645,
                        1.717909824031239,
                        0.09691402055473097
                    ],
                    [
                        -0.8545247193678643,
                        1.6504545487233353,
                        0.07185479191917958
                    ],
                    [
                        -0.8527490264668229,
                        1.6458605165854077,
                        0.014261599671640389
                    ],
                    [
                        -0.825463493404238,
                        1.7156280440262996,
                        0.037434545783110534
                    ],
                    [
                        -0.8280380647731986,
                        1.7181793901993003,
                        0.0943492697872679
                    ],
                    [
                        -0.8573504984441036,
                        1.6461382132860196,
                        0.011619492054282112
                    ],
                    [
                        -0.8589914673184986,
                        1.6507241148913967,
                        0.06929004115171651
                    ]
                ],
                [
                    [
                        0.5527983065331681,
                        1.6094533593440246,
                        -0.027652868164416824
                    ],
                    [
                        0.5668968945758966,
                        1.6148351910438836,
                        0.02278117270290965
                    ],
                    [
                        0.603168440542828,
                        1.6113930626258188,
                        0.001362652586814938
                    ],
                    [
                        0.5900538279261716,
                        1.6059178527782556,
                        -0.04965243044166661
                    ],
                    [
                        0.5527983065331681,
                        1.6055540737203575,
                        -0.02806269959797487
                    ],
                    [
                        0.5668968945758966,
                        1.6110388915304483,
                        0.02238216554571051
                    ],
                    [
                        0.5900538279261716,
                        1.6020185671545886,
                        -0.05006226187522465
                    ],
                    [
                        0.603168440542828,
                        1.6075967631123838,
                        0.0009636454296160036
                    ]
                ],
                [
                    [
                        0.9397813206740021,
                        2.3918748392506304,
                        0.22253518711340545
                    ],
                    [
                        0.9229259889900454,
                        2.3714126306328205,
                        0.26912863848521423
                    ],
                    [
                        1.0375370954362986,
                        2.3511204593292265,
                        0.2616202517054238
                    ],
                    [
                        1.0568438471278054,
                        2.3711486381547004,
                        0.21486620324885483
                    ],
                    [
                        0.9397813206740021,
                        2.387098356091145,
                        0.22125533230816044
                    ],
                    [
                        0.9229259889900454,
                        2.3667361723637725,
                        0.267875585268585
                    ],
                    [
                        1.0568438471278054,
                        2.3663721549952155,
                        0.21358634844360982
                    ],
                    [
                        1.0375370954362986,
                        2.346444001060179,
                        0.2603671984887945
                    ]
                ],
                [
                    [
                        -0.20330681617816693,
                        2.2522376189269293,
                        0.018149861984290548
                    ],
                    [
                        -0.1954374132056384,
                        2.232750202756507,
                        0.07467799747500149
                    ],
                    [
                        -0.2704472389729863,
                        2.224965981158952,
                        0.07394771011491279
                    ],
                    [
                        -0.28010360623766317,
                        2.2442679532772827,
                        0.017402176937670304
                    ],
                    [
                        -0.20330681617816693,
                        2.247098634827787,
                        0.016772875345009017
                    ],
                    [
                        -0.1954374132056384,
                        2.2277307963255977,
                        0.07333305157535547
                    ],
                    [
                        -0.28010360623766317,
                        2.2391289691781404,
                        0.016025190298388486
                    ],
                    [
                        -0.2704472389729863,
                        2.2199465747280427,
                        0.07260276421526676
                    ]
                ],
                [
                    [
                        0.17912044729066798,
                        1.610965956189229,
                        0.01703491467210204
                    ],
                    [
                        0.18078881878394584,
                        1.6272171709607237,
                        0.06560771806946658
                    ],
                    [
                        0.24561061638261472,
                        1.621388730345048,
                        0.0616625623841148
                    ],
                    [
                        0.2457915241684115,
                        1.6049712379499887,
                        0.012977208966048669
                    ],
                    [
                        0.17912044729066798,
                        1.6072530530326856,
                        0.017425156518986316
                    ],
                    [
                        0.18078881878394584,
                        1.6236072539144122,
                        0.06598713563999194
                    ],
                    [
                        0.2457915241684115,
                        1.6012583347934453,
                        0.013367450812932946
                    ],
                    [
                        0.24561061638261472,
                        1.6177788132987365,
                        0.06204197995464016
                    ]
                ]
            ],
            "Cut Time": [
                0.6302876472473145,
                0.47061729431152344,
                0.5999438762664795,
                0.35912442207336426,
                0.3319692611694336,
                0.7295558452606201,
                0.8826782703399658,
                1.231903076171875,
                0.4879903793334961,
                0.5520942211151123,
                1.280229091644287,
                0.816401481628418,
                0.7754306793212891,
                0.7542481422424316
            ],
            "Rule Time": [
                1.1102638244628906,
                3.936429500579834,
                1.6884520053863525,
                2.920159339904785,
                1.3188858032226562,
                5.798210382461548,
                9.257268190383911,
                1.0774281024932861,
                2.6198391914367676,
                2.3273603916168213,
                0.9907026290893555,
                1.0278759002685547,
                2.0714874267578125,
                1.0577611923217773
            ],
            "Between Time": [
                18.02066969871521,
                19.177961349487305,
                20.26485252380371,
                16.47378396987915,
                22.364185571670532,
                0.5828936100006104,
                27.92006254196167,
                3.167663812637329,
                12.19298791885376,
                12.865227460861206,
                17.937145948410034,
                37.55436944961548,
                22.922680616378784,
                31.58232092857361
            ]
        }
    ],
    "Explanations": [
        {
            "Branch Num": 5,
            "Decision": "Canopy Cut",
            "Explanation": "Branch too long. Pruned back to ~6 inches to keep buds"
        },
        {
            "Branch Num": 7,
            "Decision": "Canopy Cut",
            "Explanation": "Branches too close together. Removed branch with fewer buds."
        },
        {
            "Branch Num": 1,
            "Decision": "Canopy Cut",
            "Explanation": "Branch too long. Pruned back to ~6 inches to keep buds"
        },
        {
            "Branch Num": 4,
            "Decision": "Branch Vigor",
            "Explanation": "Branch is vigorous and removed to prevent shading"
        },
        {
            "Branch Num": 6,
            "Decision": "Branch Vigor",
            "Explanation": "Branch is vigorous and removed to prevent shading."
        },
        {
            "Branch Num": 3,
            "Decision": "Branch Vigor",
            "Explanation": "The branch is pruned back to keep buds."
        },
        {
            "Branch Num": 2,
            "Decision": "Bud Spacing",
            "Explanation": "Bud cluster is too close together to other buds and pruned back to keep bud count."
        }
    ],
    "Reset Answer": ""
}