{
    "Pruning Time": 168.23520708084106,
    "Cut Data": [
        {
            "Rule": [
                "Vigor",
                "Spacing",
                "Canopy",
                "Vigor",
                "Canopy",
                "Vigor"
            ],
            "Sequence": [
                1,
                2,
                3,
                4,
                5,
                6
            ],
            "Vertices": [
                [
                    [
                        0.164054562473527,
                        1.5958457406799418,
                        -0.06699442532816956
                    ],
                    [
                        0.15257489583447031,
                        1.6054701142504526,
                        -0.01831747405483618
                    ],
                    [
                        0.32763977169379893,
                        1.6354344093706714,
                        0.018893714027011867
                    ],
                    [
                        0.34339006478018863,
                        1.6265410008814651,
                        -0.02887548757249936
                    ],
                    [
                        0.164054562473527,
                        1.591497245484726,
                        -0.06699442532816956
                    ],
                    [
                        0.15257489583447031,
                        1.601225172441755,
                        -0.01831747405483618
                    ],
                    [
                        0.34339006478018863,
                        1.6221925056862492,
                        -0.02887548757249936
                    ],
                    [
                        0.32763977169379893,
                        1.6311894675619736,
                        0.018893714027011867
                    ]
                ],
                [
                    [
                        0.2690795907811533,
                        2.308785362017173,
                        0.07584836786181583
                    ],
                    [
                        0.30882832805825927,
                        2.3041669309901334,
                        0.10776366757385852
                    ],
                    [
                        0.29336970078962116,
                        2.1867373048840415,
                        0.1398778732947572
                    ],
                    [
                        0.25309850534607664,
                        2.1873869444993486,
                        0.10904794350243618
                    ],
                    [
                        0.26571993077491557,
                        2.3092529363184124,
                        0.0791753318878212
                    ],
                    [
                        0.30557850300746603,
                        2.30461921922003,
                        0.11098186555065558
                    ],
                    [
                        0.24973884533983895,
                        2.187854518800588,
                        0.11237490752844155
                    ],
                    [
                        0.29011987573882786,
                        2.187189593113938,
                        0.14309607127155427
                    ]
                ],
                [
                    [
                        -0.5456351105555668,
                        1.68612017945521,
                        0.05051643382968677
                    ],
                    [
                        -0.5251175526556794,
                        1.6939780540792353,
                        0.09891237198737907
                    ],
                    [
                        -0.3218537057896673,
                        1.7010948435192532,
                        0.0811290896819336
                    ],
                    [
                        -0.33715195884700666,
                        1.6934197101655541,
                        0.032276521519032396
                    ],
                    [
                        -0.5456351105555668,
                        1.6819837787193486,
                        0.05051643382968677
                    ],
                    [
                        -0.5251175526556794,
                        1.689945206729892,
                        0.09891237198737907
                    ],
                    [
                        -0.33715195884700666,
                        1.6892833094296926,
                        0.032276521519032396
                    ],
                    [
                        -0.3218537057896673,
                        1.6970619961699098,
                        0.0811290896819336
                    ]
                ],
                [
                    [
                        -0.6221009572581673,
                        2.3389744939384194,
                        0.0722900465719185
                    ],
                    [
                        -0.6192495442014911,
                        2.3292282928543573,
                        0.12578963804804252
                    ],
                    [
                        -0.5545109599950712,
                        2.30865152455096,
                        0.146824479162941
                    ],
                    [
                        -0.5554459057454202,
                        2.3177885880672684,
                        0.09394758566182906
                    ],
                    [
                        -0.6221009572581673,
                        2.3353728899403237,
                        0.0722900465719185
                    ],
                    [
                        -0.6192495442014911,
                        2.3257302422427797,
                        0.12578963804804252
                    ],
                    [
                        -0.5554459057454202,
                        2.3141869840691722,
                        0.09394758566182906
                    ],
                    [
                        -0.5545109599950712,
                        2.305153473939382,
                        0.146824479162941
                    ]
                ],
                [
                    [
                        0.903529619094176,
                        2.4297432400633823,
                        0.182147890055918
                    ],
                    [
                        0.8685975132584042,
                        2.4196924701954434,
                        0.22264253193525543
                    ],
                    [
                        1.0689086482586387,
                        2.3230360225140685,
                        0.29554982266741986
                    ],
                    [
                        1.108637793028503,
                        2.3307720696245426,
                        0.25680116017270815
                    ],
                    [
                        0.9007385787442834,
                        2.425783022691238,
                        0.18113203444592121
                    ],
                    [
                        0.8658717493378624,
                        2.4158248737879213,
                        0.22165043500254145
                    ],
                    [
                        1.1058467526786104,
                        2.3268118522523986,
                        0.25578530456271137
                    ],
                    [
                        1.0661828843380967,
                        2.3191684261065464,
                        0.2945577257347059
                    ]
                ],
                [
                    [
                        0.8957850314053574,
                        2.428017489151232,
                        0.17464859271564956
                    ],
                    [
                        0.8611054013029612,
                        2.418027633040069,
                        0.21523512824680696
                    ],
                    [
                        1.0776858562141267,
                        2.3007759798702936,
                        0.29406396715830463
                    ],
                    [
                        1.1175412388506754,
                        2.307963803169789,
                        0.25536125148950645
                    ],
                    [
                        0.8927253558716675,
                        2.4241479939872996,
                        0.17353496189487375
                    ],
                    [
                        0.8581171380809247,
                        2.4142484512415723,
                        0.21414748938183314
                    ],
                    [
                        1.114481563316985,
                        2.3040943080058565,
                        0.25424762066873063
                    ],
                    [
                        1.0746975929920903,
                        2.296996798071797,
                        0.2929763282933308
                    ]
                ]
            ],
            "Cut Time": [
                0.5685100555419922,
                0.6744406223297119,
                0.7558591365814209,
                0.9479215145111084,
                0.19887232780456543,
                0.9436941146850586
            ],
            "Rule Time": [
                2.360217332839966,
                3.9676053524017334,
                3.3531200885772705,
                2.467876434326172,
                2.5099780559539795,
                0.8618898391723633
            ],
            "Between Time": [
                1.575443983078003,
                20.43928074836731,
                26.159854888916016,
                17.24211311340332,
                36.03916001319885,
                18.897231578826904
            ]
        }
    ],
    "Explanations": [
        {
            "Branch Num": 1,
            "Decision": "Canopy Cut",
            "Explanation": "Branch too long. Pruned back to ~6 inches to keep buds"
        },
        {
            "Branch Num": 2,
            "Decision": "Bud Spacing",
            "Explanation": "Bud cluster is too close together to other buds and pruned back to keep bud count."
        },
        {
            "Branch Num": 3,
            "Decision": "Branch Vigor",
            "Explanation": "The branch is pruned back to keep buds."
        },
        {
            "Branch Num": 4,
            "Decision": "Branch Vigor",
            "Explanation": "Branch is vigorous and removed to prevent shading"
        },
        {
            "Branch Num": 5,
            "Decision": "Canopy Cut",
            "Explanation": "Branch too long. Pruned back to ~6 inches to keep buds"
        },
        {
            "Branch Num": 6,
            "Decision": "Branch Vigor",
            "Explanation": "Branch is vigorous and removed to prevent shading."
        },
        {
            "Branch Num": 7,
            "Decision": "Canopy Cut",
            "Explanation": "Branches too close together. Removed branch with fewer buds."
        }
    ],
    "Reset Answer": ""
}